bplate/__init__.py
bplate/__main__.py
bplate/core.py
bplate-0.2.0.dist-info/LICENSE
bplate-0.2.0.dist-info/METADATA
bplate-0.2.0.dist-info/WHEEL
bplate-0.2.0.dist-info/entry_points.txt
bplate-0.2.0.dist-info/top_level.txt
bplate-0.2.0.dist-info/RECORD
