Metadata-Version: 2.1
Name: bplate
Version: 0.2.0
Summary: Tool for storing and generating boilerplates within seconds
Home-page: https://github.com/izxxr/bplate
Author: izxxr
License: MIT
Project-URL: Documentation, https://bplate.readthedocs.io
Project-URL: Issue tracker, https://github.com/izxxr/bplate/issues
Classifier: Development Status :: 4 - Beta
Classifier: License :: OSI Approved :: MIT License
Classifier: Intended Audience :: Developers
Classifier: Natural Language :: English
Classifier: Operating System :: OS Independent
Classifier: Programming Language :: Python
Classifier: Topic :: Internet
Classifier: Topic :: Software Development
Classifier: Topic :: Utilities
Classifier: Typing :: Typed
Requires-Python: >=3.8.0
License-File: LICENSE
Requires-Dist: click (==8.*)
Requires-Dist: colorama (==0.4.*)
